napari_properties_plotter/__init__.py
napari_properties_plotter/_dock_widget.py
napari_properties_plotter/_version.py
napari_properties_plotter/components.py
napari_properties_plotter/property_plotter.py
napari_properties_plotter/utils.py
napari_properties_plotter/_tests/__init__.py
napari_properties_plotter/_tests/test_dock_widget.py
napari_properties_plotter-0.2.2.dist-info/LICENSE
napari_properties_plotter-0.2.2.dist-info/METADATA
napari_properties_plotter-0.2.2.dist-info/WHEEL
napari_properties_plotter-0.2.2.dist-info/entry_points.txt
napari_properties_plotter-0.2.2.dist-info/top_level.txt
napari_properties_plotter-0.2.2.dist-info/RECORD
