Metadata-Version: 2.1
Name: napari-properties-plotter
Version: 0.2.2
Summary: A napari plugin that automatically generates interactive plots based on layer properties.
Home-page: https://github.com/brisvag/napari-properties-plotter
Author: Lorenzo Gaifas
Author-email: lorenzo.gaifas@gmail.com
License: BSD-3
Project-URL: Bug Tracker, https://github.com/brisvag/napari-properties-plotter/issues
Project-URL: Documentation, https://github.com/brisvag/napari-properties-plotter#README.md
Project-URL: Source Code, https://github.com/brisvag/napari-properties-plotter
Project-URL: User Support, https://github.com/brisvag/napari-properties-plotter/issues
Platform: UNKNOWN
Classifier: Development Status :: 2 - Pre-Alpha
Classifier: Intended Audience :: Developers
Classifier: Framework :: napari
Classifier: Topic :: Software Development :: Testing
Classifier: Programming Language :: Python
Classifier: Programming Language :: Python :: 3
Classifier: Programming Language :: Python :: 3.7
Classifier: Programming Language :: Python :: 3.8
Classifier: Programming Language :: Python :: 3.9
Classifier: Operating System :: OS Independent
Classifier: License :: OSI Approved :: BSD License
Requires-Python: >=3.7
License-File: LICENSE
Requires-Dist: napari-plugin-engine (>=0.1.4)
Requires-Dist: numpy
Requires-Dist: pandas
Requires-Dist: pyqtgraph
Requires-Dist: qtpy
